<?xml version="1.0" ?>
<annotation>
<folder>Tianchi</folder>
<filename>aug_2_fish_19.jpg</filename>
<source>
<database>The Tianchi Database</database>
<annotation>Tianchi</annotation>
</source>
<size>
<width>466</width>
<height>437</height>
<depth>3</depth>
</size>
<object>
<name>fry</name>
<pose>Unspecified</pose>
<truncated>1</truncated>
<difficult>0</difficult>
<bndbox>
<xmin>81</xmin>
<ymin>23</ymin>
<xmax>322</xmax>
<ymax>93</ymax>
</bndbox>
</object>
<object>
<name>fry</name>
<pose>Unspecified</pose>
<truncated>1</truncated>
<difficult>0</difficult>
<bndbox>
<xmin>16</xmin>
<ymin>139</ymin>
<xmax>169</xmax>
<ymax>216</ymax>
</bndbox>
</object>
<object>
<name>fry</name>
<pose>Unspecified</pose>
<truncated>1</truncated>
<difficult>0</difficult>
<bndbox>
<xmin>8</xmin>
<ymin>208</ymin>
<xmax>172</xmax>
<ymax>284</ymax>
</bndbox>
</object>
<object>
<name>fry</name>
<pose>Unspecified</pose>
<truncated>1</truncated>
<difficult>0</difficult>
<bndbox>
<xmin>33</xmin>
<ymin>289</ymin>
<xmax>297</xmax>
<ymax>406</ymax>
</bndbox>
</object>
<object>
<name>fry</name>
<pose>Unspecified</pose>
<truncated>1</truncated>
<difficult>0</difficult>
<bndbox>
<xmin>236</xmin>
<ymin>92</ymin>
<xmax>347</xmax>
<ymax>301</ymax>
</bndbox>
</object>
<object>
<name>fry</name>
<pose>Unspecified</pose>
<truncated>1</truncated>
<difficult>0</difficult>
<bndbox>
<xmin>371</xmin>
<ymin>56</ymin>
<xmax>457</xmax>
<ymax>345</ymax>
</bndbox>
</object>
</annotation>
